django_migration_testgen/__init__.py
django_migration_testgen/apps.py
django_migration_testgen/utils.py
django_migration_testgen/management/__init__.py
django_migration_testgen/management/commands/__init__.py
django_migration_testgen/management/commands/generate_migration_tests.py
django_migration_testgen/templates/migration_test_template.py
tests/__init__.py
tests/test_management_command.py
tests/test_utils.py
django_migration_testgen-0.1.0.dist-info/METADATA
django_migration_testgen-0.1.0.dist-info/WHEEL
django_migration_testgen-0.1.0.dist-info/top_level.txt
django_migration_testgen-0.1.0.dist-info/RECORD
