Metadata-Version: 2.4
Name: django-migration-testgen
Version: 0.1.0
Summary: Auto-generate test files for Django migration files
Home-page: https://github.com/yourusername/django-migration-testgen
Author: Vijayasankar Murugan
Author-email: Vijayasankar Murugan <vijayasankarsoftware@gmail.com>
Project-URL: Homepage, https://github.com/yourusername/django-migration-testgen
Classifier: Development Status :: 4 - Beta
Classifier: Framework :: Django
Classifier: License :: OSI Approved :: MIT License
Classifier: Programming Language :: Python :: 3
Requires-Python: >=3.8
Requires-Dist: Django>=3.2
Dynamic: author
Dynamic: home-page
Dynamic: requires-python
